pyconst_utils/__init__.py
pyconst_utils/const.py
pyconst_utils-1.0.5.dist-info/licenses/LICENSE
pyconst_utils-1.0.5.dist-info/METADATA
pyconst_utils-1.0.5.dist-info/WHEEL
pyconst_utils-1.0.5.dist-info/top_level.txt
pyconst_utils-1.0.5.dist-info/RECORD
